{
    "auto": {
        "new": true,
        "id": "3593",
        "brand": "Lada",
        "model": "Niva Travel",
        "generation": "2023-02-17",
        "year": "2023-02-17",
        "modification": "1.7 Л 8 КЛ 5МТ (80 Л.С.)",
        "price": 797900,
        "credit_from": 17345,
        "power": "80",
        "fuel_consumption": "8.5",
        "max_speed": "140",
        "acceleration": "19",
        "transmission": "Механическая",
        "drive_unit": "Полный (4DW)",
        "body_type": "неизвестно",
        "volume": "1.7",
        "engine_type": "Бензиновый",
        "secure": [
            "Подушка безопасности водителя",
            "Крепления для детских сидений ISOFIX",
            "Иммобилайзер",
            "Дневные ходовые огни",
            "Система экстренного оповещения «ЭРА-ГЛОНАСС»",
            "Антиблокировочная система с электронным распределением тормозных сил (ABS, EBD)"
        ],
        "exterior": [
            "Бамперы в цвет кузова",
            "Молдинги боковых дверей в цвет кузова",
            "Накладки порогов пола",
            "Задние полностью светодиодные фонари",
            "15' стальные диски",
            "Запасное полноразмерное стальное колесо 15'"
        ],
        "interior": [
            "Заднее сиденье с раскладной спинкой в пропорции 60/40",
            "Обивка сидений ткань. Цвет черный",
            "Розетки 12V, USB"
        ],
        "comfort": [
            "Виброизоляция",
            "Гидроусилитель рулевого управления",
            "Регулируемая по высоте рулевая колонка",
            "Регулировка ремней безопасности передних сидений по высоте",
            "Воздушный фильтр салона",
            "Легкая тонировка стекол",
            "Центральный замок",
            "Электростеклоподъемники передних дверей",
            "Электропривод и обогрев наружных зеркал",
            "Аудиоподготовка"
        ],
        "multimedia": [],
        "images": [
            "LADA/Lada_Niva Travel/niva travel1734535930.jpg",
            "LADA/Lada_Niva Travel/niva travel1734535931.jpg",
            "LADA/Lada_Niva Travel/niva travel1734535932.jpg",
            "LADA/Lada_Niva Travel/niva travel1734535933.jpg",
            "LADA/Lada_Niva Travel/niva travel1734535934.jpg",
            "LADA/Lada_Niva Travel/niva travel1734535935.jpg"
        ]
    }
}